setup.py
client/__init__.py
client/cli_add_con.py
client/cli_db.py
client/cli_del_con.py
client/cli_sck.py
client/cli_win.py
client/cli_win_cnv.py
common/__init__.py
common/delog.py
common/metas.py
common/utils.py
common/variables.py
gvg_mess_cli.egg-info/PKG-INFO
gvg_mess_cli.egg-info/SOURCES.txt
gvg_mess_cli.egg-info/dependency_links.txt
gvg_mess_cli.egg-info/requires.txt
gvg_mess_cli.egg-info/top_level.txt
unit_tests/__init__.py
unit_tests/test_client.py
unit_tests/test_server.py
unit_tests/test_utils.py