Metadata-Version: 1.0
Name: gvg-mess-cli
Version: 0.0.1
Summary: gvg messanger client
Home-page: UNKNOWN
Author: Gulin Vitaliy
Author-email: gvitaly@mail.ru
License: UNKNOWN
Platform: UNKNOWN
